World_2_Data/World_to_data_script.py
World_2_Data/__init__.py
World_2_Data/_version.py
World2Data-0.0.3.dist-info/LICENSE
World2Data-0.0.3.dist-info/METADATA
World2Data-0.0.3.dist-info/WHEEL
World2Data-0.0.3.dist-info/entry_points.txt
World2Data-0.0.3.dist-info/top_level.txt
World2Data-0.0.3.dist-info/RECORD
