Metadata-Version: 2.1
Name: World2Data
Version: 0.0.3
Summary: A napari plugin in order to convert the world information to the data of a 2D/3D layer
Home-page: https://github.com/MBPhys/World2Data
Author: Marc Boucsein, Robin Koch
License: BSD-3
Platform: UNKNOWN
Classifier: Development Status :: 4 - Beta
Classifier: Intended Audience :: Developers
Classifier: Framework :: napari
Classifier: Topic :: Software Development :: Testing
Classifier: Programming Language :: Python
Classifier: Programming Language :: Python :: 3
Classifier: Programming Language :: Python :: 3.7
Classifier: Programming Language :: Python :: 3.8
Classifier: Programming Language :: Python :: 3.9
Classifier: Operating System :: OS Independent
Classifier: License :: OSI Approved :: BSD License
Requires-Python: >=3.7
License-File: LICENSE
Requires-Dist: napari-plugin-engine (>=0.1.4)
Requires-Dist: numpy
Requires-Dist: gryds
Requires-Dist: dask
Requires-Dist: scikit-image
